<?xml version="1.0"?>
<!-- Generated by Oracle Reports version 6.0.8.26.0 -->
<IPN_PREVAR>
  <LIST_G_NAGLMRD>
    <G_NAGLMRD>
      <NAGLMRD>12</NAGLMRD>
      <NANO>2024</NANO>
      <NMES>8</NMES>
      <CVRDD>1171101</CVRDD>
      <CNMBR>Azúcar</CNMBR>
      <CDSCRPCN>Corrientes</CDSCRPCN>
      <CESPCFCCN>Bolsa de  1000 g. Excluir light</CESPCFCCN>
      <LIST_G_NINFRMNT>
        <G_NINFRMNT>
          <CTPINFRMNT>H</CTPINFRMNT>
          <NPRCANTRR>849.15</NPRCANTRR>
          <NINFRMNT>1250003</NINFRMNT>
          <NFRMLR>35</NFRMLR>
          <NPANEL>4</NPANEL>
          <NVST>1</NVST>
          <NRAZON>1</NRAZON>
          <NOBSRVCN>2</NOBSRVCN>
          <NPRECIO>999</NPRECIO>
          <NPRCNRMLZD>999</NPRCNRMLZD>
          <CTPPRC>P</CTPPRC>
          <NPRCIMPTD></NPRCIMPTD>
          <CATRBTS>136- Marca: CHECK \ ---</CATRBTS>
          <NANOMESVISCMB>202306021</NANOMESVISCMB>
          <NBNFCCN></NBNFCCN>
          <NPRCNRMLZDOIMPTDANTRR>849.15</NPRCNRMLZDOIMPTDANTRR>
          <NRZNFRMLR>1</NRZNFRMLR>
          <CPRCCSTND></CPRCCSTND>
          <CP_NPRCNRMLZDANTRR>849.15</CP_NPRCNRMLZDANTRR>
          <CF_CEXCLD></CF_CEXCLD>
          <CP_EXCLDANTRR></CP_EXCLDANTRR>
          <CF_CTPPRCANTRR>O</CF_CTPPRCANTRR>
          <CF_VRCNPRCNRMLZD>17.64705882352941176</CF_VRCNPRCNRMLZD>
          <CP_NBNFCCNANTRR></CP_NBNFCCNANTRR>
        </G_NINFRMNT>
        <G_NINFRMNT>
          <CTPINFRMNT>H</CTPINFRMNT>
          <NPRCANTRR>999</NPRCANTRR>
          <NINFRMNT>1250003</NINFRMNT>
          <NFRMLR>35</NFRMLR>
          <NPANEL>14</NPANEL>
          <NVST>2</NVST>
          <NRAZON>1</NRAZON>
          <NOBSRVCN>2</NOBSRVCN>
          <NPRECIO>899</NPRECIO>
          <NPRCNRMLZD>899</NPRCNRMLZD>
          <CTPPRC>P</CTPPRC>
          <NPRCIMPTD></NPRCIMPTD>
          <CATRBTS>136- Marca: CHECK \ ---</CATRBTS>
          <NANOMESVISCMB>202306021</NANOMESVISCMB>
          <NBNFCCN></NBNFCCN>
          <NPRCNRMLZDOIMPTDANTRR>999</NPRCNRMLZDOIMPTDANTRR>
          <NRZNFRMLR>1</NRZNFRMLR>
          <CPRCCSTND></CPRCCSTND>
          <CP_NPRCNRMLZDANTRR>999</CP_NPRCNRMLZDANTRR>
          <CF_CEXCLD></CF_CEXCLD>
          <CP_EXCLDANTRR></CP_EXCLDANTRR>
          <CF_CTPPRCANTRR>P</CF_CTPPRCANTRR>
          <CF_VRCNPRCNRMLZD>-10.0100100100100100</CF_VRCNPRCNRMLZD>
          <CP_NBNFCCNANTRR></CP_NBNFCCNANTRR>
        </G_NINFRMNT>
        <G_NINFRMNT>
          <CTPINFRMNT>H</CTPINFRMNT>
          <NPRCANTRR>979</NPRCANTRR>
          <NINFRMNT>1250004</NINFRMNT>
          <NFRMLR>35</NFRMLR>
          <NPANEL>6</NPANEL>
          <NVST>1</NVST>
          <NRAZON>1</NRAZON>
          <NOBSRVCN>2</NOBSRVCN>
          <NPRECIO>999</NPRECIO>
          <NPRCNRMLZD>999</NPRCNRMLZD>
          <CTPPRC>P</CTPPRC>
          <NPRCIMPTD></NPRCIMPTD>
          <CATRBTS>136- Marca: LEDESMA \ ---</CATRBTS>
          <NANOMESVISCMB>202404021</NANOMESVISCMB>
          <NBNFCCN></NBNFCCN>
          <NPRCNRMLZDOIMPTDANTRR>979</NPRCNRMLZDOIMPTDANTRR>
          <NRZNFRMLR>1</NRZNFRMLR>
          <CPRCCSTND></CPRCCSTND>
          <CP_NPRCNRMLZDANTRR>979</CP_NPRCNRMLZDANTRR>
          <CF_CEXCLD></CF_CEXCLD>
          <CP_EXCLDANTRR></CP_EXCLDANTRR>
          <CF_CTPPRCANTRR>P</CF_CTPPRCANTRR>
          <CF_VRCNPRCNRMLZD>2.042900919305413687</CF_VRCNPRCNRMLZD>
          <CP_NBNFCCNANTRR></CP_NBNFCCNANTRR>
        </G_NINFRMNT>
        <G_NINFRMNT>
          <CTPINFRMNT>H</CTPINFRMNT>
          <NPRCANTRR>999</NPRCANTRR>
          <NINFRMNT>1250004</NINFRMNT>
          <NFRMLR>35</NFRMLR>
          <NPANEL>16</NPANEL>
          <NVST>2</NVST>
          <NRAZON>1</NRAZON>
          <NOBSRVCN>2</NOBSRVCN>
          <NPRECIO>999</NPRECIO>
          <NPRCNRMLZD>999</NPRCNRMLZD>
          <CTPPRC>P</CTPPRC>
          <NPRCIMPTD></NPRCIMPTD>
          <CATRBTS>136- Marca: LEDESMA \ ---</CATRBTS>
          <NANOMESVISCMB>202404021</NANOMESVISCMB>
          <NBNFCCN></NBNFCCN>
          <NPRCNRMLZDOIMPTDANTRR>999</NPRCNRMLZDOIMPTDANTRR>
          <NRZNFRMLR>1</NRZNFRMLR>
          <CPRCCSTND></CPRCCSTND>
          <CP_NPRCNRMLZDANTRR>999</CP_NPRCNRMLZDANTRR>
          <CF_CEXCLD></CF_CEXCLD>
          <CP_EXCLDANTRR></CP_EXCLDANTRR>
          <CF_CTPPRCANTRR>P</CF_CTPPRCANTRR>
          <CF_VRCNPRCNRMLZD>0</CF_VRCNPRCNRMLZD>
          <CP_NBNFCCNANTRR></CP_NBNFCCNANTRR>
        </G_NINFRMNT>
        <G_NINFRMNT>
          <CTPINFRMNT>S</CTPINFRMNT>
          <NPRCANTRR>1099</NPRCANTRR>
          <NINFRMNT>1250007</NINFRMNT>
          <NFRMLR>35</NFRMLR>
          <NPANEL>9</NPANEL>
          <NVST>1</NVST>
          <NRAZON>1</NRAZON>
          <NOBSRVCN>2</NOBSRVCN>
          <NPRECIO>1099</NPRECIO>
          <NPRCNRMLZD>1099</NPRCNRMLZD>
          <CTPPRC>P</CTPPRC>
          <NPRCIMPTD></NPRCIMPTD>
          <CATRBTS>136- Marca: LEDESMA \ ---</CATRBTS>
          <NANOMESVISCMB>202106011</NANOMESVISCMB>
          <NBNFCCN></NBNFCCN>
          <NPRCNRMLZDOIMPTDANTRR>1099</NPRCNRMLZDOIMPTDANTRR>
          <NRZNFRMLR>1</NRZNFRMLR>
          <CPRCCSTND></CPRCCSTND>
          <CP_NPRCNRMLZDANTRR>1099</CP_NPRCNRMLZDANTRR>
          <CF_CEXCLD></CF_CEXCLD>
          <CP_EXCLDANTRR></CP_EXCLDANTRR>
          <CF_CTPPRCANTRR>P</CF_CTPPRCANTRR>
          <CF_VRCNPRCNRMLZD>0</CF_VRCNPRCNRMLZD>
          <CP_NBNFCCNANTRR></CP_NBNFCCNANTRR>
        </G_NINFRMNT>
        <G_NINFRMNT>
          <CTPINFRMNT>S</CTPINFRMNT>
          <NPRCANTRR>1099</NPRCANTRR>
          <NINFRMNT>1250007</NINFRMNT>
          <NFRMLR>35</NFRMLR>
          <NPANEL>19</NPANEL>
          <NVST>2</NVST>
          <NRAZON>1</NRAZON>
          <NOBSRVCN>2</NOBSRVCN>
          <NPRECIO>1099</NPRECIO>
          <NPRCNRMLZD>1099</NPRCNRMLZD>
          <CTPPRC>P</CTPPRC>
          <NPRCIMPTD></NPRCIMPTD>
          <CATRBTS>136- Marca: LEDESMA \ ---</CATRBTS>
          <NANOMESVISCMB>202106011</NANOMESVISCMB>
          <NBNFCCN></NBNFCCN>
          <NPRCNRMLZDOIMPTDANTRR>1099</NPRCNRMLZDOIMPTDANTRR>
          <NRZNFRMLR>1</NRZNFRMLR>
          <CPRCCSTND></CPRCCSTND>
          <CP_NPRCNRMLZDANTRR>1099</CP_NPRCNRMLZDANTRR>
          <CF_CEXCLD></CF_CEXCLD>
          <CP_EXCLDANTRR></CP_EXCLDANTRR>
          <CF_CTPPRCANTRR>P</CF_CTPPRCANTRR>
          <CF_VRCNPRCNRMLZD>0</CF_VRCNPRCNRMLZD>
          <CP_NBNFCCNANTRR></CP_NBNFCCNANTRR>
        </G_NINFRMNT>
        <G_NINFRMNT>
          <CTPINFRMNT>S</CTPINFRMNT>
          <NPRCANTRR>1099</NPRCANTRR>
          <NINFRMNT>1250008</NINFRMNT>
          <NFRMLR>35</NFRMLR>
          <NPANEL>5</NPANEL>
          <NVST>1</NVST>
          <NRAZON>1</NRAZON>
          <NOBSRVCN>2</NOBSRVCN>
          <NPRECIO>1099</NPRECIO>
          <NPRCNRMLZD>1099</NPRCNRMLZD>
          <CTPPRC>P</CTPPRC>
          <NPRCIMPTD></NPRCIMPTD>
          <CATRBTS>136- Marca: LEDESMA \ ---</CATRBTS>
          <NANOMESVISCMB>202201021</NANOMESVISCMB>
          <NBNFCCN></NBNFCCN>
          <NPRCNRMLZDOIMPTDANTRR>1099</NPRCNRMLZDOIMPTDANTRR>
          <NRZNFRMLR>1</NRZNFRMLR>
          <CPRCCSTND></CPRCCSTND>
          <CP_NPRCNRMLZDANTRR>1099</CP_NPRCNRMLZDANTRR>
          <CF_CEXCLD></CF_CEXCLD>
          <CP_EXCLDANTRR></CP_EXCLDANTRR>
          <CF_CTPPRCANTRR>P</CF_CTPPRCANTRR>
          <CF_VRCNPRCNRMLZD>0</CF_VRCNPRCNRMLZD>
          <CP_NBNFCCNANTRR></CP_NBNFCCNANTRR>
        </G_NINFRMNT>
        <G_NINFRMNT>
          <CTPINFRMNT>S</CTPINFRMNT>
          <NPRCANTRR>1099</NPRCANTRR>
          <NINFRMNT>1250008</NINFRMNT>
          <NFRMLR>35</NFRMLR>
          <NPANEL>15</NPANEL>
          <NVST>2</NVST>
          <NRAZON>1</NRAZON>
          <NOBSRVCN>2</NOBSRVCN>
          <NPRECIO>1099</NPRECIO>
          <NPRCNRMLZD>1099</NPRCNRMLZD>
          <CTPPRC>P</CTPPRC>
          <NPRCIMPTD></NPRCIMPTD>
          <CATRBTS>136- Marca: LEDESMA \ ---</CATRBTS>
          <NANOMESVISCMB>202201021</NANOMESVISCMB>
          <NBNFCCN></NBNFCCN>
          <NPRCNRMLZDOIMPTDANTRR>1099</NPRCNRMLZDOIMPTDANTRR>
          <NRZNFRMLR>1</NRZNFRMLR>
          <CPRCCSTND></CPRCCSTND>
          <CP_NPRCNRMLZDANTRR>1099</CP_NPRCNRMLZDANTRR>
          <CF_CEXCLD></CF_CEXCLD>
          <CP_EXCLDANTRR></CP_EXCLDANTRR>
          <CF_CTPPRCANTRR>P</CF_CTPPRCANTRR>
          <CF_VRCNPRCNRMLZD>0</CF_VRCNPRCNRMLZD>
          <CP_NBNFCCNANTRR></CP_NBNFCCNANTRR>
        </G_NINFRMNT>
        <G_NINFRMNT>
          <CTPINFRMNT>S</CTPINFRMNT>
          <NPRCANTRR>1099</NPRCANTRR>
          <NINFRMNT>1250009</NINFRMNT>
          <NFRMLR>35</NFRMLR>
          <NPANEL>2</NPANEL>
          <NVST>1</NVST>
          <NRAZON>1</NRAZON>
          <NOBSRVCN>2</NOBSRVCN>
          <NPRECIO>1099</NPRECIO>
          <NPRCNRMLZD>1099</NPRCNRMLZD>
          <CTPPRC>P</CTPPRC>
          <NPRCIMPTD></NPRCIMPTD>
          <CATRBTS>136- Marca: LEDESMA \ ---</CATRBTS>
          <NANOMESVISCMB>202206011</NANOMESVISCMB>
          <NBNFCCN></NBNFCCN>
          <NPRCNRMLZDOIMPTDANTRR>1099</NPRCNRMLZDOIMPTDANTRR>
          <NRZNFRMLR>1</NRZNFRMLR>
          <CPRCCSTND></CPRCCSTND>
          <CP_NPRCNRMLZDANTRR>1099</CP_NPRCNRMLZDANTRR>
          <CF_CEXCLD></CF_CEXCLD>
          <CP_EXCLDANTRR></CP_EXCLDANTRR>
          <CF_CTPPRCANTRR>P</CF_CTPPRCANTRR>
          <CF_VRCNPRCNRMLZD>0</CF_VRCNPRCNRMLZD>
          <CP_NBNFCCNANTRR></CP_NBNFCCNANTRR>
        </G_NINFRMNT>
        <G_NINFRMNT>
          <CTPINFRMNT>S</CTPINFRMNT>
          <NPRCANTRR>1099</NPRCANTRR>
          <NINFRMNT>1250009</NINFRMNT>
          <NFRMLR>35</NFRMLR>
          <NPANEL>12</NPANEL>
          <NVST>2</NVST>
          <NRAZON>1</NRAZON>
          <NOBSRVCN>2</NOBSRVCN>
          <NPRECIO>1099</NPRECIO>
          <NPRCNRMLZD>1099</NPRCNRMLZD>
          <CTPPRC>P</CTPPRC>
          <NPRCIMPTD></NPRCIMPTD>
          <CATRBTS>136- Marca: LEDESMA \ ---</CATRBTS>
          <NANOMESVISCMB>202206011</NANOMESVISCMB>
          <NBNFCCN></NBNFCCN>
          <NPRCNRMLZDOIMPTDANTRR>1099</NPRCNRMLZDOIMPTDANTRR>
          <NRZNFRMLR>1</NRZNFRMLR>
          <CPRCCSTND></CPRCCSTND>
          <CP_NPRCNRMLZDANTRR>1099</CP_NPRCNRMLZDANTRR>
          <CF_CEXCLD></CF_CEXCLD>
          <CP_EXCLDANTRR></CP_EXCLDANTRR>
          <CF_CTPPRCANTRR>P</CF_CTPPRCANTRR>
          <CF_VRCNPRCNRMLZD>0</CF_VRCNPRCNRMLZD>
          <CP_NBNFCCNANTRR></CP_NBNFCCNANTRR>
        </G_NINFRMNT>
        <G_NINFRMNT>
          <CTPINFRMNT>S</CTPINFRMNT>
          <NPRCANTRR>1099</NPRCANTRR>
          <NINFRMNT>1250011</NINFRMNT>
          <NFRMLR>35</NFRMLR>
          <NPANEL>3</NPANEL>
          <NVST>1</NVST>
          <NRAZON>1</NRAZON>
          <NOBSRVCN>2</NOBSRVCN>
          <NPRECIO>1099</NPRECIO>
          <NPRCNRMLZD>1099</NPRCNRMLZD>
          <CTPPRC>P</CTPPRC>
          <NPRCIMPTD></NPRCIMPTD>
          <CATRBTS>136- Marca: LEDESMA \ ---</CATRBTS>
          <NANOMESVISCMB>202305021</NANOMESVISCMB>
          <NBNFCCN></NBNFCCN>
          <NPRCNRMLZDOIMPTDANTRR>1099</NPRCNRMLZDOIMPTDANTRR>
          <NRZNFRMLR>1</NRZNFRMLR>
          <CPRCCSTND></CPRCCSTND>
          <CP_NPRCNRMLZDANTRR>1099</CP_NPRCNRMLZDANTRR>
          <CF_CEXCLD></CF_CEXCLD>
          <CP_EXCLDANTRR></CP_EXCLDANTRR>
          <CF_CTPPRCANTRR>P</CF_CTPPRCANTRR>
          <CF_VRCNPRCNRMLZD>0</CF_VRCNPRCNRMLZD>
          <CP_NBNFCCNANTRR></CP_NBNFCCNANTRR>
        </G_NINFRMNT>
        <G_NINFRMNT>
          <CTPINFRMNT>S</CTPINFRMNT>
          <NPRCANTRR>1099</NPRCANTRR>
          <NINFRMNT>1250011</NINFRMNT>
          <NFRMLR>35</NFRMLR>
          <NPANEL>13</NPANEL>
          <NVST>2</NVST>
          <NRAZON>1</NRAZON>
          <NOBSRVCN>2</NOBSRVCN>
          <NPRECIO>1099</NPRECIO>
          <NPRCNRMLZD>1099</NPRCNRMLZD>
          <CTPPRC>P</CTPPRC>
          <NPRCIMPTD></NPRCIMPTD>
          <CATRBTS>136- Marca: LEDESMA \ ---</CATRBTS>
          <NANOMESVISCMB>202305021</NANOMESVISCMB>
          <NBNFCCN></NBNFCCN>
          <NPRCNRMLZDOIMPTDANTRR>1099</NPRCNRMLZDOIMPTDANTRR>
          <NRZNFRMLR>1</NRZNFRMLR>
          <CPRCCSTND></CPRCCSTND>
          <CP_NPRCNRMLZDANTRR>1099</CP_NPRCNRMLZDANTRR>
          <CF_CEXCLD></CF_CEXCLD>
          <CP_EXCLDANTRR></CP_EXCLDANTRR>
          <CF_CTPPRCANTRR>P</CF_CTPPRCANTRR>
          <CF_VRCNPRCNRMLZD>0</CF_VRCNPRCNRMLZD>
          <CP_NBNFCCNANTRR></CP_NBNFCCNANTRR>
        </G_NINFRMNT>
        <G_NINFRMNT>
          <CTPINFRMNT>T</CTPINFRMNT>
          <NPRCANTRR>1275</NPRCANTRR>
          <NINFRMNT>1270381</NINFRMNT>
          <NFRMLR>19</NFRMLR>
          <NPANEL>3</NPANEL>
          <NVST>1</NVST>
          <NRAZON>1</NRAZON>
          <NOBSRVCN>2</NOBSRVCN>
          <NPRECIO>1275</NPRECIO>
          <NPRCNRMLZD>1275</NPRCNRMLZD>
          <CTPPRC>P</CTPPRC>
          <NPRCIMPTD></NPRCIMPTD>
          <CATRBTS>136- Marca: LEDESMA \ ---</CATRBTS>
          <NANOMESVISCMB>202310011</NANOMESVISCMB>
          <NBNFCCN></NBNFCCN>
          <NPRCNRMLZDOIMPTDANTRR>1275</NPRCNRMLZDOIMPTDANTRR>
          <NRZNFRMLR>1</NRZNFRMLR>
          <CPRCCSTND></CPRCCSTND>
          <CP_NPRCNRMLZDANTRR>1275</CP_NPRCNRMLZDANTRR>
          <CF_CEXCLD></CF_CEXCLD>
          <CP_EXCLDANTRR></CP_EXCLDANTRR>
          <CF_CTPPRCANTRR>P</CF_CTPPRCANTRR>
          <CF_VRCNPRCNRMLZD>0</CF_VRCNPRCNRMLZD>
          <CP_NBNFCCNANTRR></CP_NBNFCCNANTRR>
        </G_NINFRMNT>
        <G_NINFRMNT>
          <CTPINFRMNT>S</CTPINFRMNT>
          <NPRCANTRR>1050</NPRCANTRR>
          <NINFRMNT>1270409</NINFRMNT>
          <NFRMLR>35</NFRMLR>
          <NPANEL>1</NPANEL>
          <NVST>1</NVST>
          <NRAZON>1</NRAZON>
          <NOBSRVCN>2</NOBSRVCN>
          <NPRECIO>1050</NPRECIO>
          <NPRCNRMLZD>1050</NPRCNRMLZD>
          <CTPPRC>P</CTPPRC>
          <NPRCIMPTD></NPRCIMPTD>
          <CATRBTS>136- Marca: LEDESMA \ ---</CATRBTS>
          <NANOMESVISCMB>202109011</NANOMESVISCMB>
          <NBNFCCN></NBNFCCN>
          <NPRCNRMLZDOIMPTDANTRR>1050</NPRCNRMLZDOIMPTDANTRR>
          <NRZNFRMLR>1</NRZNFRMLR>
          <CPRCCSTND></CPRCCSTND>
          <CP_NPRCNRMLZDANTRR>1050</CP_NPRCNRMLZDANTRR>
          <CF_CEXCLD></CF_CEXCLD>
          <CP_EXCLDANTRR></CP_EXCLDANTRR>
          <CF_CTPPRCANTRR>P</CF_CTPPRCANTRR>
          <CF_VRCNPRCNRMLZD>0</CF_VRCNPRCNRMLZD>
          <CP_NBNFCCNANTRR></CP_NBNFCCNANTRR>
        </G_NINFRMNT>
        <G_NINFRMNT>
          <CTPINFRMNT>S</CTPINFRMNT>
          <NPRCANTRR>1050</NPRCANTRR>
          <NINFRMNT>1270409</NINFRMNT>
          <NFRMLR>35</NFRMLR>
          <NPANEL>11</NPANEL>
          <NVST>2</NVST>
          <NRAZON>1</NRAZON>
          <NOBSRVCN>2</NOBSRVCN>
          <NPRECIO>879</NPRECIO>
          <NPRCNRMLZD>879</NPRCNRMLZD>
          <CTPPRC>O</CTPPRC>
          <NPRCIMPTD></NPRCIMPTD>
          <CATRBTS>136- Marca: LEDESMA \ ---</CATRBTS>
          <NANOMESVISCMB>202109011</NANOMESVISCMB>
          <NBNFCCN></NBNFCCN>
          <NPRCNRMLZDOIMPTDANTRR>1050</NPRCNRMLZDOIMPTDANTRR>
          <NRZNFRMLR>1</NRZNFRMLR>
          <CPRCCSTND></CPRCCSTND>
          <CP_NPRCNRMLZDANTRR>1050</CP_NPRCNRMLZDANTRR>
          <CF_CEXCLD></CF_CEXCLD>
          <CP_EXCLDANTRR></CP_EXCLDANTRR>
          <CF_CTPPRCANTRR>P</CF_CTPPRCANTRR>
          <CF_VRCNPRCNRMLZD>-16.2857142857142857</CF_VRCNPRCNRMLZD>
          <CP_NBNFCCNANTRR></CP_NBNFCCNANTRR>
        </G_NINFRMNT>
        <G_NINFRMNT>
          <CTPINFRMNT>T</CTPINFRMNT>
          <NPRCANTRR></NPRCANTRR>
          <NINFRMNT>1271814</NINFRMNT>
          <NFRMLR>19</NFRMLR>
          <NPANEL>17</NPANEL>
          <NVST>1</NVST>
          <NRAZON>1</NRAZON>
          <NOBSRVCN>2</NOBSRVCN>
          <NPRECIO>850</NPRECIO>
          <NPRCNRMLZD>850</NPRCNRMLZD>
          <CTPPRC>P</CTPPRC>
          <NPRCIMPTD></NPRCIMPTD>
          <CATRBTS>136- Marca: LATIPEÑA / AG</CATRBTS>
          <NANOMESVISCMB>202408011</NANOMESVISCMB>
          <NBNFCCN></NBNFCCN>
          <NPRCNRMLZDOIMPTDANTRR></NPRCNRMLZDOIMPTDANTRR>
          <NRZNFRMLR>1</NRZNFRMLR>
          <CPRCCSTND></CPRCCSTND>
          <CP_NPRCNRMLZDANTRR></CP_NPRCNRMLZDANTRR>
          <CF_CEXCLD></CF_CEXCLD>
          <CP_EXCLDANTRR></CP_EXCLDANTRR>
          <CF_CTPPRCANTRR>S</CF_CTPPRCANTRR>
          <CF_VRCNPRCNRMLZD></CF_VRCNPRCNRMLZD>
          <CP_NBNFCCNANTRR></CP_NBNFCCNANTRR>
        </G_NINFRMNT>
        <G_NINFRMNT>
          <CTPINFRMNT>S</CTPINFRMNT>
          <NPRCANTRR>790</NPRCANTRR>
          <NINFRMNT>1271954</NINFRMNT>
          <NFRMLR>35</NFRMLR>
          <NPANEL>7</NPANEL>
          <NVST>1</NVST>
          <NRAZON>1</NRAZON>
          <NOBSRVCN>2</NOBSRVCN>
          <NPRECIO>790</NPRECIO>
          <NPRCNRMLZD>790</NPRCNRMLZD>
          <CTPPRC>O</CTPPRC>
          <NPRCIMPTD></NPRCIMPTD>
          <CATRBTS>136- Marca: DULSAN \ ---</CATRBTS>
          <NANOMESVISCMB>201506011</NANOMESVISCMB>
          <NBNFCCN></NBNFCCN>
          <NPRCNRMLZDOIMPTDANTRR>790</NPRCNRMLZDOIMPTDANTRR>
          <NRZNFRMLR>1</NRZNFRMLR>
          <CPRCCSTND></CPRCCSTND>
          <CP_NPRCNRMLZDANTRR>790</CP_NPRCNRMLZDANTRR>
          <CF_CEXCLD></CF_CEXCLD>
          <CP_EXCLDANTRR></CP_EXCLDANTRR>
          <CF_CTPPRCANTRR>O</CF_CTPPRCANTRR>
          <CF_VRCNPRCNRMLZD>0</CF_VRCNPRCNRMLZD>
          <CP_NBNFCCNANTRR></CP_NBNFCCNANTRR>
        </G_NINFRMNT>
        <G_NINFRMNT>
          <CTPINFRMNT>S</CTPINFRMNT>
          <NPRCANTRR>790</NPRCANTRR>
          <NINFRMNT>1271954</NINFRMNT>
          <NFRMLR>35</NFRMLR>
          <NPANEL>17</NPANEL>
          <NVST>2</NVST>
          <NRAZON>1</NRAZON>
          <NOBSRVCN>2</NOBSRVCN>
          <NPRECIO>790</NPRECIO>
          <NPRCNRMLZD>790</NPRCNRMLZD>
          <CTPPRC>O</CTPPRC>
          <NPRCIMPTD></NPRCIMPTD>
          <CATRBTS>136- Marca: DULSAN \ ---</CATRBTS>
          <NANOMESVISCMB>201506011</NANOMESVISCMB>
          <NBNFCCN></NBNFCCN>
          <NPRCNRMLZDOIMPTDANTRR>790</NPRCNRMLZDOIMPTDANTRR>
          <NRZNFRMLR>1</NRZNFRMLR>
          <CPRCCSTND></CPRCCSTND>
          <CP_NPRCNRMLZDANTRR>790</CP_NPRCNRMLZDANTRR>
          <CF_CEXCLD></CF_CEXCLD>
          <CP_EXCLDANTRR></CP_EXCLDANTRR>
          <CF_CTPPRCANTRR>O</CF_CTPPRCANTRR>
          <CF_VRCNPRCNRMLZD>0</CF_VRCNPRCNRMLZD>
          <CP_NBNFCCNANTRR></CP_NBNFCCNANTRR>
        </G_NINFRMNT>
        <G_NINFRMNT>
          <CTPINFRMNT>T</CTPINFRMNT>
          <NPRCANTRR>870</NPRCANTRR>
          <NINFRMNT>1272520</NINFRMNT>
          <NFRMLR>19</NFRMLR>
          <NPANEL>5</NPANEL>
          <NVST>1</NVST>
          <NRAZON>1</NRAZON>
          <NOBSRVCN>2</NOBSRVCN>
          <NPRECIO></NPRECIO>
          <NPRCNRMLZD></NPRCNRMLZD>
          <CTPPRC>S</CTPPRC>
          <NPRCIMPTD></NPRCIMPTD>
          <CATRBTS>136- Marca: AG \ ---</CATRBTS>
          <NANOMESVISCMB>202405011</NANOMESVISCMB>
          <NBNFCCN></NBNFCCN>
          <NPRCNRMLZDOIMPTDANTRR>870</NPRCNRMLZDOIMPTDANTRR>
          <NRZNFRMLR>1</NRZNFRMLR>
          <CPRCCSTND></CPRCCSTND>
          <CP_NPRCNRMLZDANTRR>870</CP_NPRCNRMLZDANTRR>
          <CF_CEXCLD></CF_CEXCLD>
          <CP_EXCLDANTRR></CP_EXCLDANTRR>
          <CF_CTPPRCANTRR>P</CF_CTPPRCANTRR>
          <CF_VRCNPRCNRMLZD></CF_VRCNPRCNRMLZD>
          <CP_NBNFCCNANTRR></CP_NBNFCCNANTRR>
        </G_NINFRMNT>
        <G_NINFRMNT>
          <CTPINFRMNT>T</CTPINFRMNT>
          <NPRCANTRR>749.9</NPRCANTRR>
          <NINFRMNT>1272530</NINFRMNT>
          <NFRMLR>19</NFRMLR>
          <NPANEL>11</NPANEL>
          <NVST>1</NVST>
          <NRAZON>1</NRAZON>
          <NOBSRVCN>2</NOBSRVCN>
          <NPRECIO>765</NPRECIO>
          <NPRCNRMLZD>765</NPRCNRMLZD>
          <CTPPRC>P</CTPPRC>
          <NPRCIMPTD></NPRCIMPTD>
          <CATRBTS>136- Marca: AG \ ---</CATRBTS>
          <NANOMESVISCMB>202402011</NANOMESVISCMB>
          <NBNFCCN></NBNFCCN>
          <NPRCNRMLZDOIMPTDANTRR>749.9</NPRCNRMLZDOIMPTDANTRR>
          <NRZNFRMLR>1</NRZNFRMLR>
          <CPRCCSTND></CPRCCSTND>
          <CP_NPRCNRMLZDANTRR>749.9</CP_NPRCNRMLZDANTRR>
          <CF_CEXCLD></CF_CEXCLD>
          <CP_EXCLDANTRR></CP_EXCLDANTRR>
          <CF_CTPPRCANTRR>P</CF_CTPPRCANTRR>
          <CF_VRCNPRCNRMLZD>2.013601813575143352</CF_VRCNPRCNRMLZD>
          <CP_NBNFCCNANTRR></CP_NBNFCCNANTRR>
        </G_NINFRMNT>
        <G_NINFRMNT>
          <CTPINFRMNT>T</CTPINFRMNT>
          <NPRCANTRR>749.9</NPRCANTRR>
          <NINFRMNT>1272531</NINFRMNT>
          <NFRMLR>19</NFRMLR>
          <NPANEL>14</NPANEL>
          <NVST>1</NVST>
          <NRAZON>1</NRAZON>
          <NOBSRVCN>2</NOBSRVCN>
          <NPRECIO>765</NPRECIO>
          <NPRCNRMLZD>765</NPRCNRMLZD>
          <CTPPRC>P</CTPPRC>
          <NPRCIMPTD></NPRCIMPTD>
          <CATRBTS>136- Marca: AG \ ---</CATRBTS>
          <NANOMESVISCMB>201612011</NANOMESVISCMB>
          <NBNFCCN></NBNFCCN>
          <NPRCNRMLZDOIMPTDANTRR>749.9</NPRCNRMLZDOIMPTDANTRR>
          <NRZNFRMLR>1</NRZNFRMLR>
          <CPRCCSTND></CPRCCSTND>
          <CP_NPRCNRMLZDANTRR>749.9</CP_NPRCNRMLZDANTRR>
          <CF_CEXCLD></CF_CEXCLD>
          <CP_EXCLDANTRR></CP_EXCLDANTRR>
          <CF_CTPPRCANTRR>P</CF_CTPPRCANTRR>
          <CF_VRCNPRCNRMLZD>2.013601813575143352</CF_VRCNPRCNRMLZD>
          <CP_NBNFCCNANTRR></CP_NBNFCCNANTRR>
        </G_NINFRMNT>
        <G_NINFRMNT>
          <CTPINFRMNT>T</CTPINFRMNT>
          <NPRCANTRR>799.99</NPRCANTRR>
          <NINFRMNT>1272555</NINFRMNT>
          <NFRMLR>19</NFRMLR>
          <NPANEL>19</NPANEL>
          <NVST>1</NVST>
          <NRAZON>1</NRAZON>
          <NOBSRVCN>2</NOBSRVCN>
          <NPRECIO>749</NPRECIO>
          <NPRCNRMLZD>749</NPRCNRMLZD>
          <CTPPRC>P</CTPPRC>
          <NPRCIMPTD></NPRCIMPTD>
          <CATRBTS>136- Marca: LA TIPEÑA \ ---</CATRBTS>
          <NANOMESVISCMB>202209011</NANOMESVISCMB>
          <NBNFCCN></NBNFCCN>
          <NPRCNRMLZDOIMPTDANTRR>799.99</NPRCNRMLZDOIMPTDANTRR>
          <NRZNFRMLR>1</NRZNFRMLR>
          <CPRCCSTND></CPRCCSTND>
          <CP_NPRCNRMLZDANTRR>799.99</CP_NPRCNRMLZDANTRR>
          <CF_CEXCLD></CF_CEXCLD>
          <CP_EXCLDANTRR></CP_EXCLDANTRR>
          <CF_CTPPRCANTRR>P</CF_CTPPRCANTRR>
          <CF_VRCNPRCNRMLZD>-6.37382967287091089</CF_VRCNPRCNRMLZD>
          <CP_NBNFCCNANTRR></CP_NBNFCCNANTRR>
        </G_NINFRMNT>
        <G_NINFRMNT>
          <CTPINFRMNT>T</CTPINFRMNT>
          <NPRCANTRR>890</NPRCANTRR>
          <NINFRMNT>1272557</NINFRMNT>
          <NFRMLR>19</NFRMLR>
          <NPANEL>20</NPANEL>
          <NVST>1</NVST>
          <NRAZON>1</NRAZON>
          <NOBSRVCN>2</NOBSRVCN>
          <NPRECIO>950</NPRECIO>
          <NPRCNRMLZD>950</NPRCNRMLZD>
          <CTPPRC>P</CTPPRC>
          <NPRCIMPTD></NPRCIMPTD>
          <CATRBTS>136- Marca: AG \ ---</CATRBTS>
          <NANOMESVISCMB>202106011</NANOMESVISCMB>
          <NBNFCCN></NBNFCCN>
          <NPRCNRMLZDOIMPTDANTRR>890</NPRCNRMLZDOIMPTDANTRR>
          <NRZNFRMLR>1</NRZNFRMLR>
          <CPRCCSTND></CPRCCSTND>
          <CP_NPRCNRMLZDANTRR>890</CP_NPRCNRMLZDANTRR>
          <CF_CEXCLD></CF_CEXCLD>
          <CP_EXCLDANTRR></CP_EXCLDANTRR>
          <CF_CTPPRCANTRR>P</CF_CTPPRCANTRR>
          <CF_VRCNPRCNRMLZD>6.741573033707865169</CF_VRCNPRCNRMLZD>
          <CP_NBNFCCNANTRR></CP_NBNFCCNANTRR>
        </G_NINFRMNT>
        <G_NINFRMNT>
          <CTPINFRMNT>T</CTPINFRMNT>
          <NPRCANTRR>800</NPRCANTRR>
          <NINFRMNT>1272558</NINFRMNT>
          <NFRMLR>19</NFRMLR>
          <NPANEL>1</NPANEL>
          <NVST>1</NVST>
          <NRAZON>1</NRAZON>
          <NOBSRVCN>2</NOBSRVCN>
          <NPRECIO>800</NPRECIO>
          <NPRCNRMLZD>800</NPRCNRMLZD>
          <CTPPRC>P</CTPPRC>
          <NPRCIMPTD></NPRCIMPTD>
          <CATRBTS>136- Marca: AG \ ---</CATRBTS>
          <NANOMESVISCMB>201612011</NANOMESVISCMB>
          <NBNFCCN></NBNFCCN>
          <NPRCNRMLZDOIMPTDANTRR>800</NPRCNRMLZDOIMPTDANTRR>
          <NRZNFRMLR>1</NRZNFRMLR>
          <CPRCCSTND></CPRCCSTND>
          <CP_NPRCNRMLZDANTRR>800</CP_NPRCNRMLZDANTRR>
          <CF_CEXCLD></CF_CEXCLD>
          <CP_EXCLDANTRR></CP_EXCLDANTRR>
          <CF_CTPPRCANTRR>P</CF_CTPPRCANTRR>
          <CF_VRCNPRCNRMLZD>0</CF_VRCNPRCNRMLZD>
          <CP_NBNFCCNANTRR></CP_NBNFCCNANTRR>
        </G_NINFRMNT>
        <G_NINFRMNT>
          <CTPINFRMNT>T</CTPINFRMNT>
          <NPRCANTRR>1350</NPRCANTRR>
          <NINFRMNT>1276056</NINFRMNT>
          <NFRMLR>19</NFRMLR>
          <NPANEL>12</NPANEL>
          <NVST>1</NVST>
          <NRAZON>1</NRAZON>
          <NOBSRVCN>2</NOBSRVCN>
          <NPRECIO>1350</NPRECIO>
          <NPRCNRMLZD>1350</NPRCNRMLZD>
          <CTPPRC>P</CTPPRC>
          <NPRCIMPTD></NPRCIMPTD>
          <CATRBTS>136- Marca: LEDESMA \ ---</CATRBTS>
          <NANOMESVISCMB>202303011</NANOMESVISCMB>
          <NBNFCCN></NBNFCCN>
          <NPRCNRMLZDOIMPTDANTRR>1350</NPRCNRMLZDOIMPTDANTRR>
          <NRZNFRMLR>1</NRZNFRMLR>
          <CPRCCSTND></CPRCCSTND>
          <CP_NPRCNRMLZDANTRR>1350</CP_NPRCNRMLZDANTRR>
          <CF_CEXCLD></CF_CEXCLD>
          <CP_EXCLDANTRR></CP_EXCLDANTRR>
          <CF_CTPPRCANTRR>P</CF_CTPPRCANTRR>
          <CF_VRCNPRCNRMLZD>0</CF_VRCNPRCNRMLZD>
          <CP_NBNFCCNANTRR></CP_NBNFCCNANTRR>
        </G_NINFRMNT>
        <G_NINFRMNT>
          <CTPINFRMNT>T</CTPINFRMNT>
          <NPRCANTRR>1050</NPRCANTRR>
          <NINFRMNT>1276077</NINFRMNT>
          <NFRMLR>19</NFRMLR>
          <NPANEL>5</NPANEL>
          <NVST>1</NVST>
          <NRAZON>1</NRAZON>
          <NOBSRVCN>2</NOBSRVCN>
          <NPRECIO>790</NPRECIO>
          <NPRCNRMLZD>790</NPRCNRMLZD>
          <CTPPRC>O</CTPPRC>
          <NPRCIMPTD></NPRCIMPTD>
          <CATRBTS>136- Marca: DIA \ ---</CATRBTS>
          <NANOMESVISCMB>202403011</NANOMESVISCMB>
          <NBNFCCN></NBNFCCN>
          <NPRCNRMLZDOIMPTDANTRR>1050</NPRCNRMLZDOIMPTDANTRR>
          <NRZNFRMLR>1</NRZNFRMLR>
          <CPRCCSTND></CPRCCSTND>
          <CP_NPRCNRMLZDANTRR>1050</CP_NPRCNRMLZDANTRR>
          <CF_CEXCLD></CF_CEXCLD>
          <CP_EXCLDANTRR></CP_EXCLDANTRR>
          <CF_CTPPRCANTRR>P</CF_CTPPRCANTRR>
          <CF_VRCNPRCNRMLZD>-24.7619047619047619</CF_VRCNPRCNRMLZD>
          <CP_NBNFCCNANTRR></CP_NBNFCCNANTRR>
        </G_NINFRMNT>
        <G_NINFRMNT>
          <CTPINFRMNT>T</CTPINFRMNT>
          <NPRCANTRR></NPRCANTRR>
          <NINFRMNT>1276098</NINFRMNT>
          <NFRMLR>19</NFRMLR>
          <NPANEL>18</NPANEL>
          <NVST>1</NVST>
          <NRAZON>1</NRAZON>
          <NOBSRVCN>2</NOBSRVCN>
          <NPRECIO>735</NPRECIO>
          <NPRCNRMLZD>735</NPRCNRMLZD>
          <CTPPRC>O</CTPPRC>
          <NPRCIMPTD></NPRCIMPTD>
          <CATRBTS>136- Marca: MITAI / AG</CATRBTS>
          <NANOMESVISCMB>202408011</NANOMESVISCMB>
          <NBNFCCN></NBNFCCN>
          <NPRCNRMLZDOIMPTDANTRR></NPRCNRMLZDOIMPTDANTRR>
          <NRZNFRMLR>1</NRZNFRMLR>
          <CPRCCSTND></CPRCCSTND>
          <CP_NPRCNRMLZDANTRR></CP_NPRCNRMLZDANTRR>
          <CF_CEXCLD></CF_CEXCLD>
          <CP_EXCLDANTRR></CP_EXCLDANTRR>
          <CF_CTPPRCANTRR>S</CF_CTPPRCANTRR>
          <CF_VRCNPRCNRMLZD></CF_VRCNPRCNRMLZD>
          <CP_NBNFCCNANTRR></CP_NBNFCCNANTRR>
        </G_NINFRMNT>
        <G_NINFRMNT>
          <CTPINFRMNT>T</CTPINFRMNT>
          <NPRCANTRR>900</NPRCANTRR>
          <NINFRMNT>1276327</NINFRMNT>
          <NFRMLR>19</NFRMLR>
          <NPANEL>17</NPANEL>
          <NVST>1</NVST>
          <NRAZON>1</NRAZON>
          <NOBSRVCN>2</NOBSRVCN>
          <NPRECIO>1000</NPRECIO>
          <NPRCNRMLZD>1000</NPRCNRMLZD>
          <CTPPRC>P</CTPPRC>
          <NPRCIMPTD></NPRCIMPTD>
          <CATRBTS>136- Marca: AG \ ---</CATRBTS>
          <NANOMESVISCMB>202404011</NANOMESVISCMB>
          <NBNFCCN></NBNFCCN>
          <NPRCNRMLZDOIMPTDANTRR>900</NPRCNRMLZDOIMPTDANTRR>
          <NRZNFRMLR>1</NRZNFRMLR>
          <CPRCCSTND></CPRCCSTND>
          <CP_NPRCNRMLZDANTRR>900</CP_NPRCNRMLZDANTRR>
          <CF_CEXCLD></CF_CEXCLD>
          <CP_EXCLDANTRR></CP_EXCLDANTRR>
          <CF_CTPPRCANTRR>P</CF_CTPPRCANTRR>
          <CF_VRCNPRCNRMLZD>11.11111111111111111</CF_VRCNPRCNRMLZD>
          <CP_NBNFCCNANTRR></CP_NBNFCCNANTRR>
        </G_NINFRMNT>
        <G_NINFRMNT>
          <CTPINFRMNT>S</CTPINFRMNT>
          <NPRCANTRR>899</NPRCANTRR>
          <NINFRMNT>1276348</NINFRMNT>
          <NFRMLR>35</NFRMLR>
          <NPANEL>8</NPANEL>
          <NVST>1</NVST>
          <NRAZON>1</NRAZON>
          <NOBSRVCN>2</NOBSRVCN>
          <NPRECIO>879</NPRECIO>
          <NPRCNRMLZD>879</NPRCNRMLZD>
          <CTPPRC>O</CTPPRC>
          <NPRCIMPTD></NPRCIMPTD>
          <CATRBTS>136- Marca: LEDESMA \ ---</CATRBTS>
          <NANOMESVISCMB>202109011</NANOMESVISCMB>
          <NBNFCCN></NBNFCCN>
          <NPRCNRMLZDOIMPTDANTRR>899</NPRCNRMLZDOIMPTDANTRR>
          <NRZNFRMLR>1</NRZNFRMLR>
          <CPRCCSTND></CPRCCSTND>
          <CP_NPRCNRMLZDANTRR>899</CP_NPRCNRMLZDANTRR>
          <CF_CEXCLD></CF_CEXCLD>
          <CP_EXCLDANTRR></CP_EXCLDANTRR>
          <CF_CTPPRCANTRR>O</CF_CTPPRCANTRR>
          <CF_VRCNPRCNRMLZD>-2.22469410456062291</CF_VRCNPRCNRMLZD>
          <CP_NBNFCCNANTRR></CP_NBNFCCNANTRR>
        </G_NINFRMNT>
        <G_NINFRMNT>
          <CTPINFRMNT>S</CTPINFRMNT>
          <NPRCANTRR>879</NPRCANTRR>
          <NINFRMNT>1276348</NINFRMNT>
          <NFRMLR>35</NFRMLR>
          <NPANEL>18</NPANEL>
          <NVST>2</NVST>
          <NRAZON>1</NRAZON>
          <NOBSRVCN>2</NOBSRVCN>
          <NPRECIO>1050</NPRECIO>
          <NPRCNRMLZD>1050</NPRCNRMLZD>
          <CTPPRC>P</CTPPRC>
          <NPRCIMPTD></NPRCIMPTD>
          <CATRBTS>136- Marca: LEDESMA \ ---</CATRBTS>
          <NANOMESVISCMB>202109011</NANOMESVISCMB>
          <NBNFCCN></NBNFCCN>
          <NPRCNRMLZDOIMPTDANTRR>879</NPRCNRMLZDOIMPTDANTRR>
          <NRZNFRMLR>1</NRZNFRMLR>
          <CPRCCSTND></CPRCCSTND>
          <CP_NPRCNRMLZDANTRR>879</CP_NPRCNRMLZDANTRR>
          <CF_CEXCLD></CF_CEXCLD>
          <CP_EXCLDANTRR></CP_EXCLDANTRR>
          <CF_CTPPRCANTRR>O</CF_CTPPRCANTRR>
          <CF_VRCNPRCNRMLZD>19.45392491467576792</CF_VRCNPRCNRMLZD>
          <CP_NBNFCCNANTRR></CP_NBNFCCNANTRR>
        </G_NINFRMNT>
        <G_NINFRMNT>
          <CTPINFRMNT>S</CTPINFRMNT>
          <NPRCANTRR></NPRCANTRR>
          <NINFRMNT>1276386</NINFRMNT>
          <NFRMLR>35</NFRMLR>
          <NPANEL>10</NPANEL>
          <NVST>1</NVST>
          <NRAZON>1</NRAZON>
          <NOBSRVCN>2</NOBSRVCN>
          <NPRECIO>960</NPRECIO>
          <NPRCNRMLZD>960</NPRCNRMLZD>
          <CTPPRC>O</CTPPRC>
          <NPRCIMPTD></NPRCIMPTD>
          <CATRBTS>136- Marca: LA PERLA \ ---</CATRBTS>
          <NANOMESVISCMB>202404011</NANOMESVISCMB>
          <NBNFCCN></NBNFCCN>
          <NPRCNRMLZDOIMPTDANTRR></NPRCNRMLZDOIMPTDANTRR>
          <NRZNFRMLR>1</NRZNFRMLR>
          <CPRCCSTND></CPRCCSTND>
          <CP_NPRCNRMLZDANTRR></CP_NPRCNRMLZDANTRR>
          <CF_CEXCLD></CF_CEXCLD>
          <CP_EXCLDANTRR></CP_EXCLDANTRR>
          <CF_CTPPRCANTRR>S</CF_CTPPRCANTRR>
          <CF_VRCNPRCNRMLZD></CF_VRCNPRCNRMLZD>
          <CP_NBNFCCNANTRR></CP_NBNFCCNANTRR>
        </G_NINFRMNT>
        <G_NINFRMNT>
          <CTPINFRMNT>S</CTPINFRMNT>
          <NPRCANTRR>960</NPRCANTRR>
          <NINFRMNT>1276386</NINFRMNT>
          <NFRMLR>35</NFRMLR>
          <NPANEL>20</NPANEL>
          <NVST>2</NVST>
          <NRAZON>1</NRAZON>
          <NOBSRVCN>2</NOBSRVCN>
          <NPRECIO>960</NPRECIO>
          <NPRCNRMLZD>960</NPRCNRMLZD>
          <CTPPRC>O</CTPPRC>
          <NPRCIMPTD></NPRCIMPTD>
          <CATRBTS>136- Marca: LA PERLA \ ---</CATRBTS>
          <NANOMESVISCMB>202404011</NANOMESVISCMB>
          <NBNFCCN></NBNFCCN>
          <NPRCNRMLZDOIMPTDANTRR>960</NPRCNRMLZDOIMPTDANTRR>
          <NRZNFRMLR>1</NRZNFRMLR>
          <CPRCCSTND></CPRCCSTND>
          <CP_NPRCNRMLZDANTRR>960</CP_NPRCNRMLZDANTRR>
          <CF_CEXCLD></CF_CEXCLD>
          <CP_EXCLDANTRR></CP_EXCLDANTRR>
          <CF_CTPPRCANTRR>O</CF_CTPPRCANTRR>
          <CF_VRCNPRCNRMLZD>0</CF_VRCNPRCNRMLZD>
          <CP_NBNFCCNANTRR></CP_NBNFCCNANTRR>
        </G_NINFRMNT>
        <G_NINFRMNT>
          <CTPINFRMNT>T</CTPINFRMNT>
          <NPRCANTRR></NPRCANTRR>
          <NINFRMNT>1276427</NINFRMNT>
          <NFRMLR>19</NFRMLR>
          <NPANEL>4</NPANEL>
          <NVST>1</NVST>
          <NRAZON>1</NRAZON>
          <NOBSRVCN>2</NOBSRVCN>
          <NPRECIO></NPRECIO>
          <NPRCNRMLZD></NPRCNRMLZD>
          <CTPPRC>S</CTPPRC>
          <NPRCIMPTD></NPRCIMPTD>
          <CATRBTS>136- Marca: AG \ ---</CATRBTS>
          <NANOMESVISCMB>201911011</NANOMESVISCMB>
          <NBNFCCN></NBNFCCN>
          <NPRCNRMLZDOIMPTDANTRR></NPRCNRMLZDOIMPTDANTRR>
          <NRZNFRMLR>1</NRZNFRMLR>
          <CPRCCSTND></CPRCCSTND>
          <CP_NPRCNRMLZDANTRR></CP_NPRCNRMLZDANTRR>
          <CF_CEXCLD></CF_CEXCLD>
          <CP_EXCLDANTRR></CP_EXCLDANTRR>
          <CF_CTPPRCANTRR>S</CF_CTPPRCANTRR>
          <CF_VRCNPRCNRMLZD></CF_VRCNPRCNRMLZD>
          <CP_NBNFCCNANTRR></CP_NBNFCCNANTRR>
        </G_NINFRMNT>
        <G_NINFRMNT>
          <CTPINFRMNT>S</CTPINFRMNT>
          <NPRCANTRR>1050</NPRCANTRR>
          <NINFRMNT>1276487</NINFRMNT>
          <NFRMLR>35</NFRMLR>
          <NPANEL>6</NPANEL>
          <NVST>1</NVST>
          <NRAZON>1</NRAZON>
          <NOBSRVCN>2</NOBSRVCN>
          <NPRECIO>879</NPRECIO>
          <NPRCNRMLZD>879</NPRCNRMLZD>
          <CTPPRC>O</CTPPRC>
          <NPRCIMPTD></NPRCIMPTD>
          <CATRBTS>136- Marca: LEDESMA \ ---</CATRBTS>
          <NANOMESVISCMB>202108021</NANOMESVISCMB>
          <NBNFCCN></NBNFCCN>
          <NPRCNRMLZDOIMPTDANTRR>1050</NPRCNRMLZDOIMPTDANTRR>
          <NRZNFRMLR>1</NRZNFRMLR>
          <CPRCCSTND></CPRCCSTND>
          <CP_NPRCNRMLZDANTRR>1050</CP_NPRCNRMLZDANTRR>
          <CF_CEXCLD></CF_CEXCLD>
          <CP_EXCLDANTRR></CP_EXCLDANTRR>
          <CF_CTPPRCANTRR>P</CF_CTPPRCANTRR>
          <CF_VRCNPRCNRMLZD>-16.2857142857142857</CF_VRCNPRCNRMLZD>
          <CP_NBNFCCNANTRR></CP_NBNFCCNANTRR>
        </G_NINFRMNT>
        <G_NINFRMNT>
          <CTPINFRMNT>S</CTPINFRMNT>
          <NPRCANTRR>879</NPRCANTRR>
          <NINFRMNT>1276487</NINFRMNT>
          <NFRMLR>35</NFRMLR>
          <NPANEL>16</NPANEL>
          <NVST>2</NVST>
          <NRAZON>1</NRAZON>
          <NOBSRVCN>2</NOBSRVCN>
          <NPRECIO>899</NPRECIO>
          <NPRCNRMLZD>899</NPRCNRMLZD>
          <CTPPRC>O</CTPPRC>
          <NPRCIMPTD></NPRCIMPTD>
          <CATRBTS>136- Marca: LEDESMA \ ---</CATRBTS>
          <NANOMESVISCMB>202108021</NANOMESVISCMB>
          <NBNFCCN></NBNFCCN>
          <NPRCNRMLZDOIMPTDANTRR>879</NPRCNRMLZDOIMPTDANTRR>
          <NRZNFRMLR>1</NRZNFRMLR>
          <CPRCCSTND></CPRCCSTND>
          <CP_NPRCNRMLZDANTRR>879</CP_NPRCNRMLZDANTRR>
          <CF_CEXCLD></CF_CEXCLD>
          <CP_EXCLDANTRR></CP_EXCLDANTRR>
          <CF_CTPPRCANTRR>O</CF_CTPPRCANTRR>
          <CF_VRCNPRCNRMLZD>2.275312855517633675</CF_VRCNPRCNRMLZD>
          <CP_NBNFCCNANTRR></CP_NBNFCCNANTRR>
        </G_NINFRMNT>
        <G_NINFRMNT>
          <CTPINFRMNT>T</CTPINFRMNT>
          <NPRCANTRR>675</NPRCANTRR>
          <NINFRMNT>1276492</NINFRMNT>
          <NFRMLR>19</NFRMLR>
          <NPANEL>6</NPANEL>
          <NVST>1</NVST>
          <NRAZON>1</NRAZON>
          <NOBSRVCN>2</NOBSRVCN>
          <NPRECIO>749.9</NPRECIO>
          <NPRCNRMLZD>749.9</NPRCNRMLZD>
          <CTPPRC>P</CTPPRC>
          <NPRCIMPTD></NPRCIMPTD>
          <CATRBTS>136- Marca: AG \ ---</CATRBTS>
          <NANOMESVISCMB>201911011</NANOMESVISCMB>
          <NBNFCCN></NBNFCCN>
          <NPRCNRMLZDOIMPTDANTRR>675</NPRCNRMLZDOIMPTDANTRR>
          <NRZNFRMLR>1</NRZNFRMLR>
          <CPRCCSTND></CPRCCSTND>
          <CP_NPRCNRMLZDANTRR>675</CP_NPRCNRMLZDANTRR>
          <CF_CEXCLD></CF_CEXCLD>
          <CP_EXCLDANTRR></CP_EXCLDANTRR>
          <CF_CTPPRCANTRR>O</CF_CTPPRCANTRR>
          <CF_VRCNPRCNRMLZD>11.09629629629629630</CF_VRCNPRCNRMLZD>
          <CP_NBNFCCNANTRR></CP_NBNFCCNANTRR>
        </G_NINFRMNT>
        <G_NINFRMNT>
          <CTPINFRMNT>T</CTPINFRMNT>
          <NPRCANTRR>799</NPRCANTRR>
          <NINFRMNT>1276614</NINFRMNT>
          <NFRMLR>19</NFRMLR>
          <NPANEL>7</NPANEL>
          <NVST>1</NVST>
          <NRAZON>1</NRAZON>
          <NOBSRVCN>2</NOBSRVCN>
          <NPRECIO>799</NPRECIO>
          <NPRCNRMLZD>799</NPRCNRMLZD>
          <CTPPRC>P</CTPPRC>
          <NPRCIMPTD></NPRCIMPTD>
          <CATRBTS>136- Marca: LA MUÑECA \ ---</CATRBTS>
          <NANOMESVISCMB>202311011</NANOMESVISCMB>
          <NBNFCCN></NBNFCCN>
          <NPRCNRMLZDOIMPTDANTRR>799</NPRCNRMLZDOIMPTDANTRR>
          <NRZNFRMLR>1</NRZNFRMLR>
          <CPRCCSTND></CPRCCSTND>
          <CP_NPRCNRMLZDANTRR>799</CP_NPRCNRMLZDANTRR>
          <CF_CEXCLD></CF_CEXCLD>
          <CP_EXCLDANTRR></CP_EXCLDANTRR>
          <CF_CTPPRCANTRR>P</CF_CTPPRCANTRR>
          <CF_VRCNPRCNRMLZD>0</CF_VRCNPRCNRMLZD>
          <CP_NBNFCCNANTRR></CP_NBNFCCNANTRR>
        </G_NINFRMNT>
        <G_NINFRMNT>
          <CTPINFRMNT>T</CTPINFRMNT>
          <NPRCANTRR></NPRCANTRR>
          <NINFRMNT>1276638</NINFRMNT>
          <NFRMLR>19</NFRMLR>
          <NPANEL>13</NPANEL>
          <NVST>1</NVST>
          <NRAZON>1</NRAZON>
          <NOBSRVCN>2</NOBSRVCN>
          <NPRECIO>1400</NPRECIO>
          <NPRCNRMLZD>1400</NPRCNRMLZD>
          <CTPPRC>P</CTPPRC>
          <NPRCIMPTD></NPRCIMPTD>
          <CATRBTS>136- Marca: LEDESMA / AZUCEL</CATRBTS>
          <NANOMESVISCMB>202408011</NANOMESVISCMB>
          <NBNFCCN></NBNFCCN>
          <NPRCNRMLZDOIMPTDANTRR></NPRCNRMLZDOIMPTDANTRR>
          <NRZNFRMLR>1</NRZNFRMLR>
          <CPRCCSTND></CPRCCSTND>
          <CP_NPRCNRMLZDANTRR></CP_NPRCNRMLZDANTRR>
          <CF_CEXCLD></CF_CEXCLD>
          <CP_EXCLDANTRR></CP_EXCLDANTRR>
          <CF_CTPPRCANTRR>S</CF_CTPPRCANTRR>
          <CF_VRCNPRCNRMLZD></CF_VRCNPRCNRMLZD>
          <CP_NBNFCCNANTRR></CP_NBNFCCNANTRR>
        </G_NINFRMNT>
        <G_NINFRMNT>
          <CTPINFRMNT>T</CTPINFRMNT>
          <NPRCANTRR>749</NPRCANTRR>
          <NINFRMNT>1276642</NINFRMNT>
          <NFRMLR>19</NFRMLR>
          <NPANEL>14</NPANEL>
          <NVST>1</NVST>
          <NRAZON>1</NRAZON>
          <NOBSRVCN>2</NOBSRVCN>
          <NPRECIO>765</NPRECIO>
          <NPRCNRMLZD>765</NPRCNRMLZD>
          <CTPPRC>P</CTPPRC>
          <NPRCIMPTD></NPRCIMPTD>
          <CATRBTS>136- Marca: AG \ ---</CATRBTS>
          <NANOMESVISCMB>202209011</NANOMESVISCMB>
          <NBNFCCN></NBNFCCN>
          <NPRCNRMLZDOIMPTDANTRR>749</NPRCNRMLZDOIMPTDANTRR>
          <NRZNFRMLR>1</NRZNFRMLR>
          <CPRCCSTND></CPRCCSTND>
          <CP_NPRCNRMLZDANTRR>749</CP_NPRCNRMLZDANTRR>
          <CF_CEXCLD></CF_CEXCLD>
          <CP_EXCLDANTRR></CP_EXCLDANTRR>
          <CF_CTPPRCANTRR>P</CF_CTPPRCANTRR>
          <CF_VRCNPRCNRMLZD>2.136181575433911883</CF_VRCNPRCNRMLZD>
          <CP_NBNFCCNANTRR></CP_NBNFCCNANTRR>
        </G_NINFRMNT>
        <G_NINFRMNT>
          <CTPINFRMNT>T</CTPINFRMNT>
          <NPRCANTRR>669</NPRCANTRR>
          <NINFRMNT>1276657</NINFRMNT>
          <NFRMLR>19</NFRMLR>
          <NPANEL>10</NPANEL>
          <NVST>1</NVST>
          <NRAZON>1</NRAZON>
          <NOBSRVCN>2</NOBSRVCN>
          <NPRECIO>735</NPRECIO>
          <NPRCNRMLZD>735</NPRCNRMLZD>
          <CTPPRC>P</CTPPRC>
          <NPRCIMPTD></NPRCIMPTD>
          <CATRBTS>136- Marca: MITAI \ ---</CATRBTS>
          <NANOMESVISCMB>202407011</NANOMESVISCMB>
          <NBNFCCN></NBNFCCN>
          <NPRCNRMLZDOIMPTDANTRR>669</NPRCNRMLZDOIMPTDANTRR>
          <NRZNFRMLR>1</NRZNFRMLR>
          <CPRCCSTND></CPRCCSTND>
          <CP_NPRCNRMLZDANTRR>669</CP_NPRCNRMLZDANTRR>
          <CF_CEXCLD></CF_CEXCLD>
          <CP_EXCLDANTRR></CP_EXCLDANTRR>
          <CF_CTPPRCANTRR>P</CF_CTPPRCANTRR>
          <CF_VRCNPRCNRMLZD>9.865470852017937220</CF_VRCNPRCNRMLZD>
          <CP_NBNFCCNANTRR></CP_NBNFCCNANTRR>
        </G_NINFRMNT>
        <G_NINFRMNT>
          <CTPINFRMNT>T</CTPINFRMNT>
          <NPRCANTRR>710.03</NPRCANTRR>
          <NINFRMNT>1276691</NINFRMNT>
          <NFRMLR>35</NFRMLR>
          <NPANEL>3</NPANEL>
          <NVST>1</NVST>
          <NRAZON>1</NRAZON>
          <NOBSRVCN>2</NOBSRVCN>
          <NPRECIO></NPRECIO>
          <NPRCNRMLZD></NPRCNRMLZD>
          <CTPPRC>S</CTPPRC>
          <NPRCIMPTD></NPRCIMPTD>
          <CATRBTS>136- Marca: AG \ ---</CATRBTS>
          <NANOMESVISCMB>202309011</NANOMESVISCMB>
          <NBNFCCN></NBNFCCN>
          <NPRCNRMLZDOIMPTDANTRR>710.03</NPRCNRMLZDOIMPTDANTRR>
          <NRZNFRMLR>1</NRZNFRMLR>
          <CPRCCSTND></CPRCCSTND>
          <CP_NPRCNRMLZDANTRR>710.03</CP_NPRCNRMLZDANTRR>
          <CF_CEXCLD></CF_CEXCLD>
          <CP_EXCLDANTRR></CP_EXCLDANTRR>
          <CF_CTPPRCANTRR>O</CF_CTPPRCANTRR>
          <CF_VRCNPRCNRMLZD></CF_VRCNPRCNRMLZD>
          <CP_NBNFCCNANTRR></CP_NBNFCCNANTRR>
        </G_NINFRMNT>
        <G_NINFRMNT>
          <CTPINFRMNT>T</CTPINFRMNT>
          <NPRCANTRR></NPRCANTRR>
          <NINFRMNT>1276691</NINFRMNT>
          <NFRMLR>35</NFRMLR>
          <NPANEL>13</NPANEL>
          <NVST>2</NVST>
          <NRAZON>1</NRAZON>
          <NOBSRVCN>2</NOBSRVCN>
          <NPRECIO>886.36</NPRECIO>
          <NPRCNRMLZD>886.36</NPRCNRMLZD>
          <CTPPRC>P</CTPPRC>
          <NPRCIMPTD></NPRCIMPTD>
          <CATRBTS>136- Marca: AG \ ---</CATRBTS>
          <NANOMESVISCMB>202309011</NANOMESVISCMB>
          <NBNFCCN></NBNFCCN>
          <NPRCNRMLZDOIMPTDANTRR></NPRCNRMLZDOIMPTDANTRR>
          <NRZNFRMLR>1</NRZNFRMLR>
          <CPRCCSTND></CPRCCSTND>
          <CP_NPRCNRMLZDANTRR></CP_NPRCNRMLZDANTRR>
          <CF_CEXCLD></CF_CEXCLD>
          <CP_EXCLDANTRR></CP_EXCLDANTRR>
          <CF_CTPPRCANTRR>S</CF_CTPPRCANTRR>
          <CF_VRCNPRCNRMLZD></CF_VRCNPRCNRMLZD>
          <CP_NBNFCCNANTRR></CP_NBNFCCNANTRR>
        </G_NINFRMNT>
        <G_NINFRMNT>
          <CTPINFRMNT>T</CTPINFRMNT>
          <NPRCANTRR>750</NPRCANTRR>
          <NINFRMNT>1276736</NINFRMNT>
          <NFRMLR>19</NFRMLR>
          <NPANEL>8</NPANEL>
          <NVST>1</NVST>
          <NRAZON>1</NRAZON>
          <NOBSRVCN>2</NOBSRVCN>
          <NPRECIO>750</NPRECIO>
          <NPRCNRMLZD>750</NPRCNRMLZD>
          <CTPPRC>O</CTPPRC>
          <NPRCIMPTD></NPRCIMPTD>
          <CATRBTS>136- Marca: AG \ ---</CATRBTS>
          <NANOMESVISCMB>202404011</NANOMESVISCMB>
          <NBNFCCN></NBNFCCN>
          <NPRCNRMLZDOIMPTDANTRR>750</NPRCNRMLZDOIMPTDANTRR>
          <NRZNFRMLR>1</NRZNFRMLR>
          <CPRCCSTND></CPRCCSTND>
          <CP_NPRCNRMLZDANTRR>750</CP_NPRCNRMLZDANTRR>
          <CF_CEXCLD></CF_CEXCLD>
          <CP_EXCLDANTRR></CP_EXCLDANTRR>
          <CF_CTPPRCANTRR>O</CF_CTPPRCANTRR>
          <CF_VRCNPRCNRMLZD>0</CF_VRCNPRCNRMLZD>
          <CP_NBNFCCNANTRR></CP_NBNFCCNANTRR>
        </G_NINFRMNT>
        <G_NINFRMNT>
          <CTPINFRMNT>T</CTPINFRMNT>
          <NPRCANTRR></NPRCANTRR>
          <NINFRMNT>1276737</NINFRMNT>
          <NFRMLR>19</NFRMLR>
          <NPANEL>2</NPANEL>
          <NVST>1</NVST>
          <NRAZON>1</NRAZON>
          <NOBSRVCN>2</NOBSRVCN>
          <NPRECIO>849</NPRECIO>
          <NPRCNRMLZD>849</NPRCNRMLZD>
          <CTPPRC>P</CTPPRC>
          <NPRCIMPTD></NPRCIMPTD>
          <CATRBTS>136- Marca: LA MUÑECA / LEDESMA</CATRBTS>
          <NANOMESVISCMB>202408011</NANOMESVISCMB>
          <NBNFCCN></NBNFCCN>
          <NPRCNRMLZDOIMPTDANTRR></NPRCNRMLZDOIMPTDANTRR>
          <NRZNFRMLR>1</NRZNFRMLR>
          <CPRCCSTND></CPRCCSTND>
          <CP_NPRCNRMLZDANTRR></CP_NPRCNRMLZDANTRR>
          <CF_CEXCLD></CF_CEXCLD>
          <CP_EXCLDANTRR></CP_EXCLDANTRR>
          <CF_CTPPRCANTRR>S</CF_CTPPRCANTRR>
          <CF_VRCNPRCNRMLZD></CF_VRCNPRCNRMLZD>
          <CP_NBNFCCNANTRR></CP_NBNFCCNANTRR>
        </G_NINFRMNT>
        <G_NINFRMNT>
          <CTPINFRMNT>T</CTPINFRMNT>
          <NPRCANTRR>2000</NPRCANTRR>
          <NINFRMNT>1276738</NINFRMNT>
          <NFRMLR>19</NFRMLR>
          <NPANEL>9</NPANEL>
          <NVST>1</NVST>
          <NRAZON>1</NRAZON>
          <NOBSRVCN>2</NOBSRVCN>
          <NPRECIO></NPRECIO>
          <NPRCNRMLZD></NPRCNRMLZD>
          <CTPPRC>S</CTPPRC>
          <NPRCIMPTD></NPRCIMPTD>
          <CATRBTS>136- Marca: AG \ ---</CATRBTS>
          <NANOMESVISCMB>202407011</NANOMESVISCMB>
          <NBNFCCN></NBNFCCN>
          <NPRCNRMLZDOIMPTDANTRR>2000</NPRCNRMLZDOIMPTDANTRR>
          <NRZNFRMLR>1</NRZNFRMLR>
          <CPRCCSTND></CPRCCSTND>
          <CP_NPRCNRMLZDANTRR>2000</CP_NPRCNRMLZDANTRR>
          <CF_CEXCLD></CF_CEXCLD>
          <CP_EXCLDANTRR></CP_EXCLDANTRR>
          <CF_CTPPRCANTRR>P</CF_CTPPRCANTRR>
          <CF_VRCNPRCNRMLZD></CF_VRCNPRCNRMLZD>
          <CP_NBNFCCNANTRR></CP_NBNFCCNANTRR>
        </G_NINFRMNT>
      </LIST_G_NINFRMNT>
    </G_NAGLMRD>
  </LIST_G_NAGLMRD>
  <CF_NMBRTPRPRT>Normal</CF_NMBRTPRPRT>
  <CF_USER>RGONZA</CF_USER>
</IPN_PREVAR>
